scaler/CMakeLists.txt
scaler/__init__.py
scaler/about.py
scaler/version.txt
scaler/client/__init__.py
scaler/client/client.py
scaler/client/future.py
scaler/client/object_buffer.py
scaler/client/object_reference.py
scaler/client/agent/__init__.py
scaler/client/agent/client_agent.py
scaler/client/agent/disconnect_manager.py
scaler/client/agent/future_manager.py
scaler/client/agent/heartbeat_manager.py
scaler/client/agent/mixins.py
scaler/client/agent/object_manager.py
scaler/client/agent/task_manager.py
scaler/client/serializer/__init__.py
scaler/client/serializer/default.py
scaler/client/serializer/mixins.py
scaler/cluster/__init__.py
scaler/cluster/cluster.py
scaler/cluster/combo.py
scaler/cluster/object_storage_server.py
scaler/cluster/scheduler.py
scaler/entry_points/__init__.py
scaler/entry_points/cluster.py
scaler/entry_points/object_storage_server.py
scaler/entry_points/scheduler.py
scaler/entry_points/top.py
scaler/entry_points/webui.py
scaler/entry_points/worker_adapter_native.py
scaler/entry_points/worker_adapter_symphony.py
scaler/io/__init__.py
scaler/io/async_binder.py
scaler/io/async_connector.py
scaler/io/async_object_storage_connector.py
scaler/io/config.py
scaler/io/mixins.py
scaler/io/sync_connector.py
scaler/io/sync_object_storage_connector.py
scaler/io/sync_subscriber.py
scaler/io/utility.py
scaler/io/ymq/CMakeLists.txt
scaler/io/ymq/__init__.py
scaler/io/ymq/bytes.h
scaler/io/ymq/common.h
scaler/io/ymq/configuration.h
scaler/io/ymq/epoll_context.cpp
scaler/io/ymq/epoll_context.h
scaler/io/ymq/error.h
scaler/io/ymq/event_loop.h
scaler/io/ymq/event_loop_thread.cpp
scaler/io/ymq/event_loop_thread.h
scaler/io/ymq/event_manager.h
scaler/io/ymq/file_descriptor.h
scaler/io/ymq/interruptive_concurrent_queue.h
scaler/io/ymq/io_context.cpp
scaler/io/ymq/io_context.h
scaler/io/ymq/io_socket.cpp
scaler/io/ymq/io_socket.h
scaler/io/ymq/iocp_context.cpp
scaler/io/ymq/iocp_context.h
scaler_gxu-1.12.4.dist-info/METADATA
scaler_gxu-1.12.4.dist-info/WHEEL
scaler_gxu-1.12.4.dist-info/entry_points.txt
scaler_gxu-1.12.4.dist-info/RECORD
scaler_gxu-1.12.4.dist-info/licenses/LICENSE
scaler_gxu-1.12.4.dist-info/licenses/LICENSE.spdx
scaler_gxu-1.12.4.dist-info/licenses/NOTICE
