Metadata-Version: 2.2
Name: scaler-gxu
Version: 1.12.4
Summary: Scaler Distribution Framework
Author-Email: Citi <opensource@citi.com>
License: Apache 2.0
Classifier: Programming Language :: Python :: 3
Classifier: License :: OSI Approved :: Apache Software License
Classifier: Intended Audience :: Developers
Classifier: Operating System :: OS Independent
Classifier: Topic :: System :: Distributed Computing
Project-URL: Home, https://github.com/Citi/scaler
Requires-Python: >=3.8
Requires-Dist: bidict
Requires-Dist: cloudpickle
Requires-Dist: psutil==7.1.0
Requires-Dist: pycapnp==2.1.0
Requires-Dist: pyzmq
Requires-Dist: sortedcontainers==2.4.0
Requires-Dist: tblib
Requires-Dist: aiohttp
Requires-Dist: graphlib-backport; python_version < "3.9"
Provides-Extra: uvloop
Requires-Dist: uvloop; platform_system != "Windows" and extra == "uvloop"
Provides-Extra: gui
Requires-Dist: nicegui[plotly]==2.24.2; extra == "gui"
Provides-Extra: graphblas
Requires-Dist: python-graphblas; extra == "graphblas"
Requires-Dist: numpy==1.24.4; python_version == "3.8" and extra == "graphblas"
Requires-Dist: numpy==2.0.2; python_version == "3.9" and extra == "graphblas"
Requires-Dist: numpy==2.2.6; python_version >= "3.10" and extra == "graphblas"
Provides-Extra: all
Requires-Dist: nicegui[plotly]==2.24.2; extra == "all"
Requires-Dist: python-graphblas; extra == "all"
Requires-Dist: numpy==1.24.4; python_version == "3.8" and extra == "all"
Requires-Dist: numpy==2.0.2; python_version == "3.9" and extra == "all"
Requires-Dist: numpy==2.2.6; python_version >= "3.10" and extra == "all"
Requires-Dist: uvloop; platform_system != "Windows" and extra == "all"
